pypleasant/__init__.py
pypleasant/__main__.py
pypleasant/api.py
pypleasant/artifacts.py
pypleasant/cli.py
pypleasant/pathparser.py
pypleasant/pleasant.py
pypleasant-2.0.0.dist-info/LICENSE
pypleasant-2.0.0.dist-info/METADATA
pypleasant-2.0.0.dist-info/WHEEL
pypleasant-2.0.0.dist-info/entry_points.txt
pypleasant-2.0.0.dist-info/top_level.txt
pypleasant-2.0.0.dist-info/RECORD
