Metadata-Version: 2.1
Name: pypleasant
Version: 2.0.0
Summary: Python library and script to access the API of the pleasant password server.
Home-page: https://github.com/dbermuehler/pypleasant
Author: Dominik Bermühler
Author-email: dominik.bermuehler@googlemail.com
License: MIT
Platform: UNKNOWN
Classifier: Programming Language :: Python :: 3.6
Classifier: Programming Language :: Python :: 3.7
Classifier: Programming Language :: Python :: 3.8
Classifier: Programming Language :: Python :: 3.9
Classifier: Operating System :: OS Independent
Classifier: Topic :: Security
Classifier: Environment :: Console
Classifier: Intended Audience :: Developers
Classifier: Intended Audience :: System Administrators
Classifier: License :: OSI Approved :: MIT License
Requires-Python: >=3.6
Requires-Dist: requests
